{"_notifyingListeners":false,"_scopeListeners":[],"_eventProcessors":[],"_breadcrumbs":[{"timestamp":1673460747.94,"category":"electron","message":"app.ready","type":"ui"},{"timestamp":1673460747.945,"category":"electron","message":"app.session-created","type":"ui"},{"timestamp":1673460747.946,"category":"electron","message":"app.web-contents-created","type":"ui"},{"timestamp":1673460747.947,"category":"electron","message":"app.browser-window-created","type":"ui"},{"timestamp":1673460747.948,"category":"electron","message":"window.show","type":"ui","data":{}},{"timestamp":1673460747.954,"category":"electron","message":"renderer.load-url","type":"ui","data":{}},{"timestamp":1673460747.954,"category":"electron","message":"window.show","type":"ui","data":{}},{"timestamp":1673460747.954,"category":"console","level":"log","message":"[PERFORMANCE] tried to end event with no start time: waiting for app ready "},{"timestamp":1673460748.195,"category":"electron","message":"app.web-contents-created","type":"ui"},{"timestamp":1673460748.198,"category":"electron","message":"renderer.load-url","type":"ui","data":{}},{"timestamp":1673460748.201,"category":"console","level":"error","message":"(node:15985) [DEP0005] DeprecationWarning: Buffer() is deprecated due to security and usability issues. Please use the Buffer.alloc(), Buffer.allocUnsafe(), or Buffer.from() methods instead.\n(Use `gitkraken --trace-deprecation ...` to show where the warning was created)"},{"timestamp":1673460748.207,"category":"electron","message":"app.gpu-info-update","type":"ui"},{"timestamp":1673460748.207,"category":"electron","message":"window.focus","type":"ui","data":{}},{"timestamp":1673460748.207,"category":"electron","message":"app.browser-window-focus","type":"ui"},{"timestamp":1673460748.209,"category":"console","level":"error","message":"(node:15985) [DEP0106] DeprecationWarning: crypto.createDecipher is deprecated."},{"timestamp":1673460748.26,"category":"electron","message":"renderer.dom-ready","type":"ui","data":{"id":1,"url":"app:///src/render/static/entryPoints/splash/index.html"}},{"timestamp":1673460748.287,"category":"console","level":"log","message":"state:  unavailable"},{"timestamp":1673460748.299,"category":"electron","message":"app.web-contents-created","type":"ui"},{"timestamp":1673460748.315,"category":"electron","message":"app.browser-window-created","type":"ui"},{"timestamp":1673460748.32,"category":"electron","message":"renderer.load-url","type":"ui","data":{}},{"timestamp":1673460748.613,"category":"electron","message":"renderer.dom-ready","type":"ui","data":{"id":2,"url":"app:///src/render/static/entryPoints/requestHandler/index.html?loadSettings={\"clientType\"%3A\"NORMAL\"%2C\"exitWhenDone\"%3Afalse%2C\"resourcePath\"%3A\"%2Fopt%2Fgitkraken%2Fresources%2Fapp.asar\"%2C\"mode\"%3A\"production\"%2C\"title\"%3A\"Request Handler\"%2C\"version\"%3A\"9.0.1\"%2C\"appDataPath\"%3A\"%2Fhome%2Fgisbi%2F.config\"%2C\"appPath\"%3A\"%2Fopt%2Fgitkraken%2Fresources%2Fapp.asar\"}"}},{"timestamp":1673460748.9,"category":"console","level":"error","message":"Error: 2\n    at handleError (/opt/gitkraken/resources/app.asar/src/main/static/main.bundle.js:2:107321)\n    at handleError.next (<anonymous>)\n    at next (/opt/gitkraken/resources/app.asar/src/main/static/main.bundle.js:2:4475992)\n    at proc (/opt/gitkraken/resources/app.asar/src/main/static/main.bundle.js:2:4475765)\n    at pe.<computed> (/opt/gitkraken/resources/app.asar/src/main/static/main.bundle.js:2:4471096)\n    at /opt/gitkraken/resources/app.asar/src/main/static/main.bundle.js:2:4475548\n    at digestEffect (/opt/gitkraken/resources/app.asar/src/main/static/main.bundle.js:2:4476620)\n    at next (/opt/gitkraken/resources/app.asar/src/main/static/main.bundle.js:2:4476057)\n    at Object.currCb [as cont] (/opt/gitkraken/resources/app.asar/src/main/static/main.bundle.js:2:4476382)\n    at end (/opt/gitkraken/resources/app.asar/src/main/static/main.bundle.js:2:4474723)\n    at abort (/opt/gitkraken/resources/app.asar/src/main/static/main.bundle.js:2:4474084)\n    at Object.D.cont (/opt/gitkraken/resources/app.asar/src/main/static/main.bundle.js:2:4474179)\n    at next (/opt/gitkraken/resources/app.asar/src/main/static/main.bundle.js:2:4476136)\n    at currCb (/opt/gitkraken/resources/app.asar/src/main/static/main.bundle.js:2:4476382)\n    at /opt/gitkraken/resources/app.asar/src/main/static/main.bundle.js:2:4469694\n    at processTicksAndRejections (node:internal/process/task_queues:96:5)"},{"timestamp":1673460748.901,"category":"console","level":"error","message":"The above error occurred in task call\n"},{"timestamp":1673460748.901,"category":"console","level":"error","message":"(node:15985) UnhandledPromiseRejectionWarning: Error: 2\n    at handleError (/opt/gitkraken/resources/app.asar/src/main/static/main.bundle.js:2:107321)\n    at handleError.next (<anonymous>)\n    at next (/opt/gitkraken/resources/app.asar/src/main/static/main.bundle.js:2:4475992)\n    at proc (/opt/gitkraken/resources/app.asar/src/main/static/main.bundle.js:2:4475765)\n    at pe.<computed> (/opt/gitkraken/resources/app.asar/src/main/static/main.bundle.js:2:4471096)\n    at /opt/gitkraken/resources/app.asar/src/main/static/main.bundle.js:2:4475548\n    at digestEffect (/opt/gitkraken/resources/app.asar/src/main/static/main.bundle.js:2:4476620)\n    at next (/opt/gitkraken/resources/app.asar/src/main/static/main.bundle.js:2:4476057)\n    at Object.currCb [as cont] (/opt/gitkraken/resources/app.asar/src/main/static/main.bundle.js:2:4476382)\n    at end (/opt/gitkraken/resources/app.asar/src/main/static/main.bundle.js:2:4474723)\n    at abort (/opt/gitkraken/resources/app.asar/src/main/static/main.bundle.js:2:4474084)\n    at Object.D.cont (/opt/gitkraken/resources/app.asar/src/main/static/main.bundle.js:2:4474179)\n    at next (/opt/gitkraken/resources/app.asar/src/main/static/main.bundle.js:2:4476136)\n    at currCb (/opt/gitkraken/resources/app.asar/src/main/static/main.bundle.js:2:4476382)\n    at /opt/gitkraken/resources/app.asar/src/main/static/main.bundle.js:2:4469694\n    at processTicksAndRejections (node:internal/process/task_queues:96:5)"},{"timestamp":1673460748.901,"category":"console","level":"error","message":"(node:15985) UnhandledPromiseRejectionWarning: Unhandled promise rejection. This error originated either by throwing inside of an async function without a catch block, or by rejecting a promise which was not handled with .catch(). To terminate the node process on unhandled promise rejection, use the CLI flag `--unhandled-rejections=strict` (see https://nodejs.org/api/cli.html#cli_unhandled_rejections_mode). (rejection id: 1)"},{"timestamp":1673460748.901,"category":"console","level":"error","message":"(node:15985) UnhandledPromiseRejectionWarning: Error: 2\n    at handleError (/opt/gitkraken/resources/app.asar/src/main/static/main.bundle.js:2:107321)\n    at handleError.next (<anonymous>)\n    at next (/opt/gitkraken/resources/app.asar/src/main/static/main.bundle.js:2:4475992)\n    at proc (/opt/gitkraken/resources/app.asar/src/main/static/main.bundle.js:2:4475765)\n    at pe.<computed> (/opt/gitkraken/resources/app.asar/src/main/static/main.bundle.js:2:4471096)\n    at /opt/gitkraken/resources/app.asar/src/main/static/main.bundle.js:2:4475548\n    at digestEffect (/opt/gitkraken/resources/app.asar/src/main/static/main.bundle.js:2:4476620)\n    at next (/opt/gitkraken/resources/app.asar/src/main/static/main.bundle.js:2:4476057)\n    at Object.currCb [as cont] (/opt/gitkraken/resources/app.asar/src/main/static/main.bundle.js:2:4476382)\n    at end (/opt/gitkraken/resources/app.asar/src/main/static/main.bundle.js:2:4474723)\n    at abort (/opt/gitkraken/resources/app.asar/src/main/static/main.bundle.js:2:4474084)\n    at Object.D.cont (/opt/gitkraken/resources/app.asar/src/main/static/main.bundle.js:2:4474179)\n    at next (/opt/gitkraken/resources/app.asar/src/main/static/main.bundle.js:2:4476136)\n    at currCb (/opt/gitkraken/resources/app.asar/src/main/static/main.bundle.js:2:4476382)\n    at /opt/gitkraken/resources/app.asar/src/main/static/main.bundle.js:2:4469694\n    at processTicksAndRejections (node:internal/process/task_queues:96:5)"},{"timestamp":1673460748.901,"category":"console","level":"error","message":"(node:15985) UnhandledPromiseRejectionWarning: Unhandled promise rejection. This error originated either by throwing inside of an async function without a catch block, or by rejecting a promise which was not handled with .catch(). To terminate the node process on unhandled promise rejection, use the CLI flag `--unhandled-rejections=strict` (see https://nodejs.org/api/cli.html#cli_unhandled_rejections_mode). (rejection id: 2)"},{"timestamp":1673460748.901,"category":"console","level":"error","message":"(node:15985) UnhandledPromiseRejectionWarning: Error: 2\n    at handleError (/opt/gitkraken/resources/app.asar/src/main/static/main.bundle.js:2:107321)\n    at handleError.next (<anonymous>)\n    at next (/opt/gitkraken/resources/app.asar/src/main/static/main.bundle.js:2:4475992)\n    at proc (/opt/gitkraken/resources/app.asar/src/main/static/main.bundle.js:2:4475765)\n    at pe.<computed> (/opt/gitkraken/resources/app.asar/src/main/static/main.bundle.js:2:4471096)\n    at /opt/gitkraken/resources/app.asar/src/main/static/main.bundle.js:2:4475548\n    at digestEffect (/opt/gitkraken/resources/app.asar/src/main/static/main.bundle.js:2:4476620)\n    at next (/opt/gitkraken/resources/app.asar/src/main/static/main.bundle.js:2:4476057)\n    at Object.currCb [as cont] (/opt/gitkraken/resources/app.asar/src/main/static/main.bundle.js:2:4476382)\n    at end (/opt/gitkraken/resources/app.asar/src/main/static/main.bundle.js:2:4474723)\n    at abort (/opt/gitkraken/resources/app.asar/src/main/static/main.bundle.js:2:4474084)\n    at Object.D.cont (/opt/gitkraken/resources/app.asar/src/main/static/main.bundle.js:2:4474179)\n    at next (/opt/gitkraken/resources/app.asar/src/main/static/main.bundle.js:2:4476136)\n    at currCb (/opt/gitkraken/resources/app.asar/src/main/static/main.bundle.js:2:4476382)\n    at /opt/gitkraken/resources/app.asar/src/main/static/main.bundle.js:2:4469694\n    at processTicksAndRejections (node:internal/process/task_queues:96:5)"},{"timestamp":1673460748.901,"category":"console","level":"error","message":"(node:15985) UnhandledPromiseRejectionWarning: Unhandled promise rejection. This error originated either by throwing inside of an async function without a catch block, or by rejecting a promise which was not handled with .catch(). To terminate the node process on unhandled promise rejection, use the CLI flag `--unhandled-rejections=strict` (see https://nodejs.org/api/cli.html#cli_unhandled_rejections_mode). (rejection id: 3)"},{"timestamp":1673460748.901,"category":"console","level":"error","message":"(node:15985) UnhandledPromiseRejectionWarning: Error: 2\n    at handleError (/opt/gitkraken/resources/app.asar/src/main/static/main.bundle.js:2:107321)\n    at handleError.next (<anonymous>)\n    at next (/opt/gitkraken/resources/app.asar/src/main/static/main.bundle.js:2:4475992)\n    at proc (/opt/gitkraken/resources/app.asar/src/main/static/main.bundle.js:2:4475765)\n    at pe.<computed> (/opt/gitkraken/resources/app.asar/src/main/static/main.bundle.js:2:4471096)\n    at /opt/gitkraken/resources/app.asar/src/main/static/main.bundle.js:2:4475548\n    at digestEffect (/opt/gitkraken/resources/app.asar/src/main/static/main.bundle.js:2:4476620)\n    at next (/opt/gitkraken/resources/app.asar/src/main/static/main.bundle.js:2:4476057)\n    at Object.currCb [as cont] (/opt/gitkraken/resources/app.asar/src/main/static/main.bundle.js:2:4476382)\n    at end (/opt/gitkraken/resources/app.asar/src/main/static/main.bundle.js:2:4474723)\n    at abort (/opt/gitkraken/resources/app.asar/src/main/static/main.bundle.js:2:4474084)\n    at Object.D.cont (/opt/gitkraken/resources/app.asar/src/main/static/main.bundle.js:2:4474179)\n    at next (/opt/gitkraken/resources/app.asar/src/main/static/main.bundle.js:2:4476136)\n    at currCb (/opt/gitkraken/resources/app.asar/src/main/static/main.bundle.js:2:4476382)\n    at /opt/gitkraken/resources/app.asar/src/main/static/main.bundle.js:2:4469694\n    at processTicksAndRejections (node:internal/process/task_queues:96:5)"},{"timestamp":1673460748.901,"category":"console","level":"error","message":"(node:15985) UnhandledPromiseRejectionWarning: Unhandled promise rejection. This error originated either by throwing inside of an async function without a catch block, or by rejecting a promise which was not handled with .catch(). To terminate the node process on unhandled promise rejection, use the CLI flag `--unhandled-rejections=strict` (see https://nodejs.org/api/cli.html#cli_unhandled_rejections_mode). (rejection id: 4)"},{"timestamp":1673460748.901,"category":"console","level":"error","message":"(node:15985) UnhandledPromiseRejectionWarning: Error: 2\n    at handleError (/opt/gitkraken/resources/app.asar/src/main/static/main.bundle.js:2:107321)\n    at handleError.next (<anonymous>)\n    at next (/opt/gitkraken/resources/app.asar/src/main/static/main.bundle.js:2:4475992)\n    at proc (/opt/gitkraken/resources/app.asar/src/main/static/main.bundle.js:2:4475765)\n    at pe.<computed> (/opt/gitkraken/resources/app.asar/src/main/static/main.bundle.js:2:4471096)\n    at /opt/gitkraken/resources/app.asar/src/main/static/main.bundle.js:2:4475548\n    at digestEffect (/opt/gitkraken/resources/app.asar/src/main/static/main.bundle.js:2:4476620)\n    at next (/opt/gitkraken/resources/app.asar/src/main/static/main.bundle.js:2:4476057)\n    at Object.currCb [as cont] (/opt/gitkraken/resources/app.asar/src/main/static/main.bundle.js:2:4476382)\n    at end (/opt/gitkraken/resources/app.asar/src/main/static/main.bundle.js:2:4474723)\n    at abort (/opt/gitkraken/resources/app.asar/src/main/static/main.bundle.js:2:4474084)\n    at Object.D.cont (/opt/gitkraken/resources/app.asar/src/main/static/main.bundle.js:2:4474179)\n    at next (/opt/gitkraken/resources/app.asar/src/main/static/main.bundle.js:2:4476136)\n    at currCb (/opt/gitkraken/resources/app.asar/src/main/static/main.bundle.js:2:4476382)\n    at /opt/gitkraken/resources/app.asar/src/main/static/main.bundle.js:2:4469694\n    at processTicksAndRejections (node:internal/process/task_queues:96:5)"},{"timestamp":1673460748.902,"category":"console","level":"error","message":"(node:15985) UnhandledPromiseRejectionWarning: Unhandled promise rejection. This error originated either by throwing inside of an async function without a catch block, or by rejecting a promise which was not handled with .catch(). To terminate the node process on unhandled promise rejection, use the CLI flag `--unhandled-rejections=strict` (see https://nodejs.org/api/cli.html#cli_unhandled_rejections_mode). (rejection id: 5)"},{"timestamp":1673460749.401,"category":"console","level":"log","message":"state:  checking"},{"timestamp":1673460749.412,"category":"electron","message":"renderer.dom-ready","type":"ui","data":{"id":3,"url":"app:///src/render/static/entryPoints/main/index.html?loadSettings={\"bootUpEnvironment\"%3A{\"SHELL\"%3A\"%2Fusr%2Fbin%2Fzsh\"%2C\"GNOME_KEYRING_CONTROL\"%3A\"%2Fhome%2Fgisbi%2F.cache%2Fkeyring-AIB7X1\"%2C\"SSH_AUTH_SOCK\"%3A\"%2Fhome%2Fgisbi%2F.cache%2Fkeyring-AIB7X1%2Fssh\"%2C\"GTK_MODULES\"%3A\"canberra-gtk-module\"%2C\"XDG_SEAT\"%3A\"seat0\"%2C\"PWD\"%3A\"%2Fhome%2Fgisbi\"%2C\"LOGNAME\"%3A\"gisbi\"%2C\"XDG_SESSION_TYPE\"%3A\"x11\"%2C\"_\"%3A\"%2Fsbin%2Frofi\"%2C\"XAUTHORITY\"%3A\"%2Fhome%2Fgisbi%2F.lyxauth\"%2C\"DESKTOP_STARTUP_ID\"%3A\"rofi%2Fgitkraken%2F15961-0-arch_TIME8555947\"%2C\"MOTD_SHOWN\"%3A\"pam\"%2C\"HOME\"%3A\"%2Fhome%2Fgisbi\"%2C\"LANG\"%3A\"en_US.UTF-8\"%2C\"XDG_SESSION_CLASS\"%3A\"user\"%2C\"TERM\"%3A\"linux\"%2C\"USER\"%3A\"gisbi\"%2C\"DISPLAY\"%3A\"%3A0\"%2C\"SHLVL\"%3A\"2\"%2C\"XDG_VTNR\"%3A\"2\"%2C\"XDG_RUNTIME_DIR\"%3A\"%2Frun%2Fuser%2F1000\"%2C\"DEBUGINFOD_URLS\"%3A\"https%3A%2F%2Fdebuginfod.archlinux.org \"%2C\"XDG_DATA_DIRS\"%3A\"%2Fhome%2Fgisbi%2F.local%2Fshare%2Fflatpak%2Fexports%2Fshare%3A%2Fvar%2Flib%2Fflatpak%2Fexports%2Fshare%3A%2Fusr%2Flocal%2Fshare%3A%2Fusr%2Fshare%3A%2Fvar%2Flib%2Fsnapd%2Fdesktop\"%2C\"PATH\"%3A\"%2Fsbin%3A%2Fbin%3A%2Fusr%2Flocal%2Fsbin%3A%2Fusr%2Flocal%2Fbin%3A%2Fusr%2Fbin%3A%2Fusr%2Fsbin%3A%2Fusr%2Flib%2Fjvm%2Fdefault%2Fbin%3A%2Fusr%2Fbin%2Fsite_perl%3A%2Fusr%2Fbin%2Fvendor_perl%3A%2Fusr%2Fbin%2Fcore_perl%3A%2Fvar%2Flib%2Fsnapd%2Fsnap%2Fbin\"%2C\"DBUS_SESSION_BUS_ADDRESS\"%3A\"unix%3Apath%3D%2Ftmp%2Fdbus-w7m0eHNdWC%2Cguid%3D48296da1f0d630bdd75b935d63bedac1\"%2C\"MAIL\"%3A\"%2Fvar%2Fspool%2Fmail%2Fgisbi\"%2C\"OLDPWD\"%3A\"%2Fhome%2Fgisbi\"%2C\"CHROME_DESKTOP\"%3A\"GitKraken.desktop\"%2C\"ORIGINAL_XDG_CURRENT_DESKTOP\"%3A\"undefined\"}%2C\"clientType\"%3A\"NORMAL\"%2C\"exitWhenDone\"%3Afalse%2C\"overrideActivityLogLevel\"%3A\"\"%2C\"printNexxuz\"%3Afalse%2C\"printVersion\"%3Afalse%2C\"resourcePath\"%3A\"%2Fopt%2Fgitkraken%2Fresources%2Fapp.asar\"%2C\"runPerformanceTimings\"%3Afalse%2C\"showSplashScreen\"%3Atrue%2C\"appDataPath\"%3A\"%2Fhome%2Fgisbi%2F.config\"%2C\"mode\"%3A\"production\"%2C\"appPath\"%3A\"%2Fopt%2Fgitkraken%2Fresources%2Fapp.asar\"%2C\"appLocale\"%3A\"en-US\"%2C\"title\"%3A\"GitKraken\"%2C\"version\"%3A\"9.0.1\"}"}},{"timestamp":1673460749.67,"category":"electron","message":"window.show","type":"ui","data":{"id":3,"url":"app:///src/render/static/entryPoints/main/index.html?loadSettings={\"bootUpEnvironment\"%3A{\"SHELL\"%3A\"%2Fusr%2Fbin%2Fzsh\"%2C\"GNOME_KEYRING_CONTROL\"%3A\"%2Fhome%2Fgisbi%2F.cache%2Fkeyring-AIB7X1\"%2C\"SSH_AUTH_SOCK\"%3A\"%2Fhome%2Fgisbi%2F.cache%2Fkeyring-AIB7X1%2Fssh\"%2C\"GTK_MODULES\"%3A\"canberra-gtk-module\"%2C\"XDG_SEAT\"%3A\"seat0\"%2C\"PWD\"%3A\"%2Fhome%2Fgisbi\"%2C\"LOGNAME\"%3A\"gisbi\"%2C\"XDG_SESSION_TYPE\"%3A\"x11\"%2C\"_\"%3A\"%2Fsbin%2Frofi\"%2C\"XAUTHORITY\"%3A\"%2Fhome%2Fgisbi%2F.lyxauth\"%2C\"DESKTOP_STARTUP_ID\"%3A\"rofi%2Fgitkraken%2F15961-0-arch_TIME8555947\"%2C\"MOTD_SHOWN\"%3A\"pam\"%2C\"HOME\"%3A\"%2Fhome%2Fgisbi\"%2C\"LANG\"%3A\"en_US.UTF-8\"%2C\"XDG_SESSION_CLASS\"%3A\"user\"%2C\"TERM\"%3A\"linux\"%2C\"USER\"%3A\"gisbi\"%2C\"DISPLAY\"%3A\"%3A0\"%2C\"SHLVL\"%3A\"2\"%2C\"XDG_VTNR\"%3A\"2\"%2C\"XDG_RUNTIME_DIR\"%3A\"%2Frun%2Fuser%2F1000\"%2C\"DEBUGINFOD_URLS\"%3A\"https%3A%2F%2Fdebuginfod.archlinux.org \"%2C\"XDG_DATA_DIRS\"%3A\"%2Fhome%2Fgisbi%2F.local%2Fshare%2Fflatpak%2Fexports%2Fshare%3A%2Fvar%2Flib%2Fflatpak%2Fexports%2Fshare%3A%2Fusr%2Flocal%2Fshare%3A%2Fusr%2Fshare%3A%2Fvar%2Flib%2Fsnapd%2Fdesktop\"%2C\"PATH\"%3A\"%2Fsbin%3A%2Fbin%3A%2Fusr%2Flocal%2Fsbin%3A%2Fusr%2Flocal%2Fbin%3A%2Fusr%2Fbin%3A%2Fusr%2Fsbin%3A%2Fusr%2Flib%2Fjvm%2Fdefault%2Fbin%3A%2Fusr%2Fbin%2Fsite_perl%3A%2Fusr%2Fbin%2Fvendor_perl%3A%2Fusr%2Fbin%2Fcore_perl%3A%2Fvar%2Flib%2Fsnapd%2Fsnap%2Fbin\"%2C\"DBUS_SESSION_BUS_ADDRESS\"%3A\"unix%3Apath%3D%2Ftmp%2Fdbus-w7m0eHNdWC%2Cguid%3D48296da1f0d630bdd75b935d63bedac1\"%2C\"MAIL\"%3A\"%2Fvar%2Fspool%2Fmail%2Fgisbi\"%2C\"OLDPWD\"%3A\"%2Fhome%2Fgisbi\"%2C\"CHROME_DESKTOP\"%3A\"GitKraken.desktop\"%2C\"ORIGINAL_XDG_CURRENT_DESKTOP\"%3A\"undefined\"}%2C\"clientType\"%3A\"NORMAL\"%2C\"exitWhenDone\"%3Afalse%2C\"overrideActivityLogLevel\"%3A\"\"%2C\"printNexxuz\"%3Afalse%2C\"printVersion\"%3Afalse%2C\"resourcePath\"%3A\"%2Fopt%2Fgitkraken%2Fresources%2Fapp.asar\"%2C\"runPerformanceTimings\"%3Afalse%2C\"showSplashScreen\"%3Atrue%2C\"appDataPath\"%3A\"%2Fhome%2Fgisbi%2F.config\"%2C\"mode\"%3A\"production\"%2C\"appPath\"%3A\"%2Fopt%2Fgitkraken%2Fresources%2Fapp.asar\"%2C\"appLocale\"%3A\"en-US\"%2C\"title\"%3A\"GitKraken\"%2C\"version\"%3A\"9.0.1\"}"}},{"timestamp":1673460749.67,"category":"electron","message":"window.close","type":"ui","data":{"id":1,"url":"app:///src/render/static/entryPoints/splash/index.html"}},{"timestamp":1673460749.685,"category":"electron","message":"renderer.destroyed","type":"ui","data":{"id":1,"url":"app:///src/render/static/entryPoints/splash/index.html"}},{"timestamp":1673460749.695,"category":"electron","message":"window.closed","type":"ui","data":{"id":1,"url":"app:///src/render/static/entryPoints/splash/index.html"}},{"timestamp":1673460749.712,"category":"electron","message":"window.focus","type":"ui","data":{"id":3,"url":"app:///src/render/static/entryPoints/main/index.html?loadSettings={\"bootUpEnvironment\"%3A{\"SHELL\"%3A\"%2Fusr%2Fbin%2Fzsh\"%2C\"GNOME_KEYRING_CONTROL\"%3A\"%2Fhome%2Fgisbi%2F.cache%2Fkeyring-AIB7X1\"%2C\"SSH_AUTH_SOCK\"%3A\"%2Fhome%2Fgisbi%2F.cache%2Fkeyring-AIB7X1%2Fssh\"%2C\"GTK_MODULES\"%3A\"canberra-gtk-module\"%2C\"XDG_SEAT\"%3A\"seat0\"%2C\"PWD\"%3A\"%2Fhome%2Fgisbi\"%2C\"LOGNAME\"%3A\"gisbi\"%2C\"XDG_SESSION_TYPE\"%3A\"x11\"%2C\"_\"%3A\"%2Fsbin%2Frofi\"%2C\"XAUTHORITY\"%3A\"%2Fhome%2Fgisbi%2F.lyxauth\"%2C\"DESKTOP_STARTUP_ID\"%3A\"rofi%2Fgitkraken%2F15961-0-arch_TIME8555947\"%2C\"MOTD_SHOWN\"%3A\"pam\"%2C\"HOME\"%3A\"%2Fhome%2Fgisbi\"%2C\"LANG\"%3A\"en_US.UTF-8\"%2C\"XDG_SESSION_CLASS\"%3A\"user\"%2C\"TERM\"%3A\"linux\"%2C\"USER\"%3A\"gisbi\"%2C\"DISPLAY\"%3A\"%3A0\"%2C\"SHLVL\"%3A\"2\"%2C\"XDG_VTNR\"%3A\"2\"%2C\"XDG_RUNTIME_DIR\"%3A\"%2Frun%2Fuser%2F1000\"%2C\"DEBUGINFOD_URLS\"%3A\"https%3A%2F%2Fdebuginfod.archlinux.org \"%2C\"XDG_DATA_DIRS\"%3A\"%2Fhome%2Fgisbi%2F.local%2Fshare%2Fflatpak%2Fexports%2Fshare%3A%2Fvar%2Flib%2Fflatpak%2Fexports%2Fshare%3A%2Fusr%2Flocal%2Fshare%3A%2Fusr%2Fshare%3A%2Fvar%2Flib%2Fsnapd%2Fdesktop\"%2C\"PATH\"%3A\"%2Fsbin%3A%2Fbin%3A%2Fusr%2Flocal%2Fsbin%3A%2Fusr%2Flocal%2Fbin%3A%2Fusr%2Fbin%3A%2Fusr%2Fsbin%3A%2Fusr%2Flib%2Fjvm%2Fdefault%2Fbin%3A%2Fusr%2Fbin%2Fsite_perl%3A%2Fusr%2Fbin%2Fvendor_perl%3A%2Fusr%2Fbin%2Fcore_perl%3A%2Fvar%2Flib%2Fsnapd%2Fsnap%2Fbin\"%2C\"DBUS_SESSION_BUS_ADDRESS\"%3A\"unix%3Apath%3D%2Ftmp%2Fdbus-w7m0eHNdWC%2Cguid%3D48296da1f0d630bdd75b935d63bedac1\"%2C\"MAIL\"%3A\"%2Fvar%2Fspool%2Fmail%2Fgisbi\"%2C\"OLDPWD\"%3A\"%2Fhome%2Fgisbi\"%2C\"CHROME_DESKTOP\"%3A\"GitKraken.desktop\"%2C\"ORIGINAL_XDG_CURRENT_DESKTOP\"%3A\"undefined\"}%2C\"clientType\"%3A\"NORMAL\"%2C\"exitWhenDone\"%3Afalse%2C\"overrideActivityLogLevel\"%3A\"\"%2C\"printNexxuz\"%3Afalse%2C\"printVersion\"%3Afalse%2C\"resourcePath\"%3A\"%2Fopt%2Fgitkraken%2Fresources%2Fapp.asar\"%2C\"runPerformanceTimings\"%3Afalse%2C\"showSplashScreen\"%3Atrue%2C\"appDataPath\"%3A\"%2Fhome%2Fgisbi%2F.config\"%2C\"mode\"%3A\"production\"%2C\"appPath\"%3A\"%2Fopt%2Fgitkraken%2Fresources%2Fapp.asar\"%2C\"appLocale\"%3A\"en-US\"%2C\"title\"%3A\"GitKraken\"%2C\"version\"%3A\"9.0.1\"}"}},{"timestamp":1673460749.712,"category":"electron","message":"app.browser-window-focus","type":"ui"},{"timestamp":1673460750.456,"category":"console","level":"log","message":"state:  unavailable"},{"timestamp":1673460754.615,"category":"console","level":"error","message":"(node:15985) UnhandledPromiseRejectionWarning: Error: GK-Providers-502 - \"<html>\\r\\n<head><title>502 Bad Gateway</title></head>\\r\\n<body>\\r\\n<center><h1>502 Bad Gateway</h1></center>\\r\\n</body>\\r\\n</html>\\r\\n\"\n    at checkForErrors (/opt/gitkraken/resources/app.asar/src/main/static/main.bundle.js:2:919029)\n    at performGraphQLRequest (/opt/gitkraken/resources/app.asar/src/main/static/main.bundle.js:2:919657)\n    at performGraphQLRequest.next (<anonymous>)\n    at next (/opt/gitkraken/resources/app.asar/src/main/static/main.bundle.js:2:4475992)\n    at Object.currCb [as cont] (/opt/gitkraken/resources/app.asar/src/main/static/main.bundle.js:2:4476382)\n    at end (/opt/gitkraken/resources/app.asar/src/main/static/main.bundle.js:2:4474723)\n    at Object.D.cont (/opt/gitkraken/resources/app.asar/src/main/static/main.bundle.js:2:4474221)\n    at next (/opt/gitkraken/resources/app.asar/src/main/static/main.bundle.js:2:4476041)\n    at currCb (/opt/gitkraken/resources/app.asar/src/main/static/main.bundle.js:2:4476382)\n    at processTicksAndRejections (node:internal/process/task_queues:96:5)"},{"timestamp":1673460754.615,"category":"console","level":"error","message":"(node:15985) UnhandledPromiseRejectionWarning: Unhandled promise rejection. This error originated either by throwing inside of an async function without a catch block, or by rejecting a promise which was not handled with .catch(). To terminate the node process on unhandled promise rejection, use the CLI flag `--unhandled-rejections=strict` (see https://nodejs.org/api/cli.html#cli_unhandled_rejections_mode). (rejection id: 6)"},{"timestamp":1673473210.571,"category":"electron","message":"screen.display-removed","type":"ui"},{"timestamp":1673473213.489,"category":"electron","message":"app.gpu-process-crashed","type":"ui"},{"timestamp":1673473213.489,"category":"electron","message":"app.child-process-gone","type":"ui"},{"timestamp":1673473213.491,"type":"process","category":"child-process","message":"'GPU' process exited with 'abnormal-exit'","level":"warning","data":{"type":"GPU","reason":"abnormal-exit","exitCode":8704,"serviceName":"GPU"}},{"timestamp":1673473213.618,"category":"electron","message":"app.gpu-info-update","type":"ui"}],"_attachments":[],"_user":{},"_tags":{"arch":"x64","appId":"54c0c30e90272e5e68ae4cc3b3357debcf1661ce"},"_extra":{},"_contexts":{},"_sdkProcessingMetadata":{},"_session":{"sid":"26e83c1b75ca4fe4b85d0478d65fa3d5","init":false,"started":"2023-01-11T18:12:27.940Z","timestamp":"2023-01-11T21:40:13.494Z","status":"ok","errors":0,"duration":12465.553999900818,"attrs":{"release":"GitKraken@9.0.1","environment":"production"}}}